LICENSE.txt
MANIFEST.in
README.rst
setup.py
derivcheck/__init__.py
derivcheck/basic_example.py
derivcheck/test_derivcheck.py
derivcheck/version.py
derivcheck.egg-info/PKG-INFO
derivcheck.egg-info/SOURCES.txt
derivcheck.egg-info/dependency_links.txt
derivcheck.egg-info/requires.txt
derivcheck.egg-info/top_level.txt