Metadata-Version: 1.2
Name: derivcheck
Version: 1.1.5
Summary: A robust and very sensitive tester for analytic derivatives.
Home-page: https://github.com/theochem/derivcheck
Author: Toon Verstraelen
Author-email: Toon.Verstraelen@UGent.be
License: UNKNOWN
Platform: UNKNOWN
Classifier: Environment :: Console
Classifier: Intended Audience :: Science/Research
Classifier: License :: OSI Approved :: GNU General Public License v3 or later (GPLv3+)
Classifier: Operating System :: POSIX :: Linux
Classifier: Programming Language :: Python :: 2.7
Classifier: Programming Language :: Python :: 3
Requires-Python: >=2.7
